{"currentPlayerIndex":1,"mainBoard":{"goldDeck":[78,69,52,74,71,70,53,64,66,54,67,58,57,55,43,60,68,62,46,65,76,44,75,79,77,41,63,61,56,45],"sharedResourceCards":[17,29],"resourceDeck":[36,24,5,11,35,25,30,27,31,19,18,37,20,1,22,16,6,2,12,26,34,32,38],"sharedGoldCards":[51,42],"sharedObjectiveCards":[94,95]},"currentGamePhase":"FINALPHASE","answered":{"0":false,"1":true,"2":false,"3":false},"chat":[{"author":2,"content":"Ei"},{"author":1,"content":"no no grazie a te"},{"author":2,"content":"Froscio"},{"author":0,"content":"dqd"},{"author":1,"content":"ghei"},{"author":2,"content":"puzzolente"}],"players":[{"objectiveCardOptions":[],"color":"YELLOW","starterCard":81,"allElements":{"MANUSCRIPT":0,"QUILL":0,"INKWELL":0,"EMPTY":0,"FUNGI":1,"INSECT":3,"ANIMAL":0,"PLANT":1},"centerResource":{"10":"FUNGI","39":"INSECT"},"objectivesWon":0,"nickname":"fede","placedCardsMap":{"10":"FRONT","39":"FRONT"},"objectiveCard":101,"points":2,"playerBoard":[[81],[10],[39]],"handCardsMap":{"80":"FRONT","4":"FRONT","59":"FRONT"}},{"objectiveCardOptions":[],"color":"RED","starterCard":84,"allElements":{"MANUSCRIPT":0,"QUILL":1,"INKWELL":0,"EMPTY":0,"FUNGI":3,"INSECT":3,"ANIMAL":5,"PLANT":1},"centerResource":{"9":"FUNGI","21":"ANIMAL","7":"FUNGI","23":"ANIMAL","47":"FUNGI","15":"PLANT"},"objectivesWon":0,"nickname":"franco","placedCardsMap":{"21":"FRONT","7":"FRONT","23":"FRONT","9":"FRONT","47":"BACK","15":"FRONT"},"objectiveCard":97,"points":1,"playerBoard":[[-1,-1,9,21],[23,7,47,84],[-1,15,-1,-1]],"handCardsMap":{"72":"FRONT","33":"FRONT","73":"FRONT"}},{"objectiveCardOptions":[],"color":"GREEN","starterCard":85,"allElements":{"MANUSCRIPT":0,"QUILL":0,"INKWELL":0,"EMPTY":0,"FUNGI":3,"INSECT":2,"ANIMAL":2,"PLANT":4},"centerResource":{"8":"FUNGI","40":"INSECT","3":"FUNGI","28":"ANIMAL","13":"PLANT","14":"PLANT"},"objectivesWon":0,"nickname":"Pole","placedCardsMap":{"3":"FRONT","8":"FRONT","40":"FRONT","28":"FRONT","13":"FRONT","14":"FRONT"},"objectiveCard":89,"points":3,"playerBoard":[[13,8,-1],[-1,85,28],[-1,-1,14],[-1,-1,40],[-1,-1,3]],"handCardsMap":{"48":"FRONT","49":"FRONT","50":"FRONT"}}],"currentGameTurn":"PLACINGPHASE","turnToPlay":2147483647,"prevGamePhase":"MAINPHASE"}