{"currentPlayerIndex":0,"mainBoard":{"goldDeck":[61,43,42,75,49,58,77,64,69,68,80,74,57,47,50,73,78,56,45,67,54,55,44,72,51,71,63,60,65,53,48,62,46,52,41,70],"sharedResourceCards":[10,36],"resourceDeck":[11,23,40,27,28,6,37,31,16,3,35,7,33,20,26,14,24,12,4,9,18,13,25,30,15,17,5,8,21,2,34,22,1,38],"sharedGoldCards":[59,79],"sharedObjectiveCards":[91,93]},"currentGamePhase":"MAINPHASE","answered":{"0":false,"1":false,"2":false,"3":false},"chat":"bohNonC\u0027èLaChat","players":[{"objectiveCardOptions":[],"color":"RED","starterCard":81,"allElements":{"MANUSCRIPT":0,"FUNGI":2,"QUILL":0,"ANIMAL":2,"EMPTY":0,"INKWELL":0,"INSECT":2,"PLANT":2},"centerResource":{},"objectivesWon":0,"nickname":"a","placedCardsMap":{"81":"BACK"},"objectiveCard":98,"points":0,"playerBoard":[[81]],"handCardsMap":{"76":"FRONT","19":"FRONT","39":"FRONT"}},{"objectiveCardOptions":[],"color":"GREEN","starterCard":85,"allElements":{"MANUSCRIPT":0,"FUNGI":2,"QUILL":0,"ANIMAL":2,"EMPTY":0,"INKWELL":0,"INSECT":2,"PLANT":2},"centerResource":{},"objectivesWon":0,"nickname":"b","placedCardsMap":{"85":"BACK"},"objectiveCard":99,"points":0,"playerBoard":[[85]],"handCardsMap":{"32":"FRONT","29":"FRONT","66":"FRONT"}}],"currentGameTurn":"PLACINGPHASE","turnToPlay":2147483647,"prevGamePhase":""}